{"extra":{"now":1626527850000,"fatal_item_ids":[],"logid":"202107172117300102122031494B2C56EC"},"log_pb":{"impr_id":"202107172117300102122031494B2C56EC"},"status_code":0,"data":{"trending_desc":"实时上升热点","recommend_list":null,"word_list":[{"group_id":"6985420399762134308","sentence_id":"354303","event_time":1626515168,"drift_info":null,"aweme_infos":null,"word":"王彦霖王鹤棣新郎伴郎同框","position":1,"related_words":null,"view_count":47651334,"hotlist_param":"{\"version\":1}","sentence_tag":2004,"label":5,"hot_value":9682484,"challenge_id":"","word_cover":{"uri":"tos-cn-p-0015/af3489f2561042638144223db9b4be0a","url_list":["https://p6.douyinpic.com/img/tos-cn-p-0015/af3489f2561042638144223db9b4be0a~noop.jpeg?from=3218412987","https://p9.douyinpic.com/img/tos-cn-p-0015/af3489f2561042638144223db9b4be0a~noop.jpeg?from=3218412987","https://p3.douyinpic.com/img/tos-cn-p-0015/af3489f2561042638144223db9b4be0a~noop.jpeg?from=3218412987"]},"video_count":2,"word_type":1},{"drift_info":null,"hotlist_param":"{\"version\":1}","sentence_tag":2004,"label":5,"position":2,"sentence_id":"354338","related_words":null,"aweme_infos":null,"hot_value":9001523,"word_cover":{"url_list":["https://p6.douyinpic.com/img/tos-cn-p-0015/4bbbb29cb15e4013bf829e4fd7bcc281_1626515711~noop.jpeg?from=3218412987","https://p29.douyinpic.com/img/tos-cn-p-0015/4bbbb29cb15e4013bf829e4fd7bcc281_1626515711~noop.jpeg?from=3218412987","https://p3.douyinpic.com/img/tos-cn-p-0015/4bbbb29cb15e4013bf829e4fd7bcc281_1626515711~noop.jpeg?from=3218412987"],"uri":"tos-cn-p-0015/4bbbb29cb15e4013bf829e4fd7bcc281_1626515711"},"group_id":"6985419809138677023","word_type":1,"word":"乐华家族氛围感大片","can_extend_detail":false,"view_count":49869262,"challenge_id":"","video_count":19,"event_time":1626518664},{"related_words":null,"aweme_infos":null,"sentence_tag":2006,"group_id":"6985416873840448776","word_type":1,"event_time":1626495895,"view_count":49914573,"word":"乐华年会土到家了","hot_value":7822319,"challenge_id":"","video_count":4,"drift_info":null,"label":3,"word_cover":{"uri":"tos-cn-p-0015/bdf039377cc64df99ba6a1e5fe781f8b_1626443637","url_list":["https://p26.douyinpic.com/img/tos-cn-p-0015/bdf039377cc64df99ba6a1e5fe781f8b_1626443637~noop.jpeg?from=3218412987","https://p29.douyinpic.com/img/tos-cn-p-0015/bdf039377cc64df99ba6a1e5fe781f8b_1626443637~noop.jpeg?from=3218412987","https://p3.douyinpic.com/img/tos-cn-p-0015/bdf039377cc64df99ba6a1e5fe781f8b_1626443637~noop.jpeg?from=3218412987"]},"position":3,"sentence_id":"354004","hotlist_param":"{\"version\":1}"},{"position":4,"event_time":1626505878,"can_extend_detail":false,"sentence_tag":2004,"challenge_id":"","video_count":12,"group_id":"6983506501643506984","word_type":1,"drift_info":null,"word_cover":{"uri":"tos-cn-p-0015/c124ee6460c547f8ae62225fad61e2d5","url_list":["https://p6.douyinpic.com/img/tos-cn-p-0015/c124ee6460c547f8ae62225fad61e2d5~noop.jpeg?from=3218412987","https://p9.douyinpic.com/img/tos-cn-p-0015/c124ee6460c547f8ae62225fad61e2d5~noop.jpeg?from=3218412987","https://p3.douyinpic.com/img/tos-cn-p-0015/c124ee6460c547f8ae62225fad61e2d5~noop.jpeg?from=3218412987"]},"sentence_id":"354128","related_words":null,"view_count":47271724,"hotlist_param":"{\"version\":1}","word":"薛之谦新歌变废为宝","label":5,"hot_value":7778330,"aweme_infos":null},{"challenge_id":"","group_id":"6804617352315933959","word_type":1,"event_time":1626488628,"hotlist_param":"{\"version\":1}","related_words":null,"view_count":49055376,"drift_info":null,"sentence_tag":13000,"hot_value":7645214,"position":5,"sentence_id":"353953","word":"红太狼好帅","label":3,"word_cover":{"uri":"tos-cn-p-0015/be847d7b9c144195999e3eaa84464dcd","url_list":["https://p6.douyinpic.com/img/tos-cn-p-0015/be847d7b9c144195999e3eaa84464dcd~noop.jpeg?from=3218412987","https://p26.douyinpic.com/img/tos-cn-p-0015/be847d7b9c144195999e3eaa84464dcd~noop.jpeg?from=3218412987","https://p3.douyinpic.com/img/tos-cn-p-0015/be847d7b9c144195999e3eaa84464dcd~noop.jpeg?from=3218412987"]},"video_count":6,"can_extend_detail":false,"aweme_infos":null},{"label":5,"hot_value":7621410,"word_cover":{"uri":"tos-cn-p-0015/0a770efa85cc48969c2b81ab7c361b2d_1626515550","url_list":["https://p3.douyinpic.com/img/tos-cn-p-0015/0a770efa85cc48969c2b81ab7c361b2d_1626515550~noop.jpeg?from=3218412987","https://p26.douyinpic.com/img/tos-cn-p-0015/0a770efa85cc48969c2b81ab7c361b2d_1626515550~noop.jpeg?from=3218412987","https://p29.douyinpic.com/img/tos-cn-p-0015/0a770efa85cc48969c2b81ab7c361b2d_1626515550~noop.jpeg?from=3218412987"]},"position":6,"video_count":3,"group_id":"6985420781329995015","view_count":48229674,"word":"王一博扑克飞镖帅炸了","sentence_tag":2004,"aweme_infos":null,"sentence_id":"354337","word_type":1,"event_time":1626518629,"related_words":null,"drift_info":null,"hotlist_param":"{\"version\":1}","challenge_id":""},{"related_words":null,"drift_info":null,"challenge_id":"","position":7,"group_id":"6985417846621558029","event_time":1626498397,"sentence_tag":2004,"word":"虞书欣用西瓜拍大片","word_type":1,"sentence_id":"354030","view_count":49157070,"hot_value":7410002,"hotlist_param":"{\"version\":1}","label":5,"word_cover":{"uri":"tos-cn-p-0015/198cb206f1854cf493842ab62b1af8d9","url_list":["https://p29.douyinpic.com/img/tos-cn-p-0015/198cb206f1854cf493842ab62b1af8d9~noop.jpeg?from=3218412987","https://p6.douyinpic.com/img/tos-cn-p-0015/198cb206f1854cf493842ab62b1af8d9~noop.jpeg?from=3218412987","https://p3.douyinpic.com/img/tos-cn-p-0015/198cb206f1854cf493842ab62b1af8d9~noop.jpeg?from=3218412987"]},"video_count":11,"aweme_infos":null},{"word_type":1,"hot_value":7363687,"video_count":14,"event_time":1626479394,"view_count":48576400,"challenge_id":"","position":8,"sentence_id":"353924","drift_info":null,"aweme_infos":null,"sentence_tag":2003,"word":"蔡徐坤与自己的剪辑师相认","label":3,"word_cover":{"uri":"tos-cn-p-0015/c89307b966804fad96425c541562509a_1626443474","url_list":["https://p9.douyinpic.com/img/tos-cn-p-0015/c89307b966804fad96425c541562509a_1626443474~noop.jpeg?from=3218412987","https://p3.douyinpic.com/img/tos-cn-p-0015/c89307b966804fad96425c541562509a_1626443474~noop.jpeg?from=3218412987","https://p6.douyinpic.com/img/tos-cn-p-0015/c89307b966804fad96425c541562509a_1626443474~noop.jpeg?from=3218412987"]},"group_id":"6985412487353505032","related_words":null,"hotlist_param":"{\"version\":1}"},{"word_cover":{"uri":"tos-cn-p-0015/f8bf331a8cd142cd8e18b99febaa5743","url_list":["https://p9.douyinpic.com/img/tos-cn-p-0015/f8bf331a8cd142cd8e18b99febaa5743~noop.jpeg?from=3218412987","https://p6.douyinpic.com/img/tos-cn-p-0015/f8bf331a8cd142cd8e18b99febaa5743~noop.jpeg?from=3218412987","https://p3.douyinpic.com/img/tos-cn-p-0015/f8bf331a8cd142cd8e18b99febaa5743~noop.jpeg?from=3218412987"]},"position":9,"word_type":1,"sentence_id":"353716","word":"山东人眼里的山航","challenge_id":"","group_id":"6984477650190423327","related_words":null,"aweme_infos":null,"label":3,"sentence_tag":20005,"hotlist_param":"{\"version\":1}","video_count":32,"event_time":1626433502,"view_count":47361344,"drift_info":null,"hot_value":7362527},{"drift_info":null,"word":"8G少年彭昱畅","position":10,"video_count":25,"word_type":1,"label":0,"hot_value":7333768,"challenge_id":"","event_time":1626447278,"view_count":49482875,"sentence_tag":2001,"word_cover":{"uri":"tos-cn-p-0015/f3db3e0fdda445a9a5645b0de62bfc58_1626443648","url_list":["https://p29.douyinpic.com/img/tos-cn-p-0015/f3db3e0fdda445a9a5645b0de62bfc58_1626443648~noop.jpeg?from=3218412987","https://p9.douyinpic.com/img/tos-cn-p-0015/f3db3e0fdda445a9a5645b0de62bfc58_1626443648~noop.jpeg?from=3218412987","https://p26.douyinpic.com/img/tos-cn-p-0015/f3db3e0fdda445a9a5645b0de62bfc58_1626443648~noop.jpeg?from=3218412987"]},"group_id":"6985412517146121485","sentence_id":"353876","related_words":null,"hotlist_param":"{\"version\":1}","aweme_infos":null},{"view_count":47506665,"hot_value":7321095,"related_words":null,"group_id":"6573985819604833543","can_extend_detail":true,"word_type":1,"hotlist_param":"{\"version\":1}","word":"李子峰结婚","label":5,"detail_info":{},"aweme_infos":null,"challenge_id":"","event_time":1626519806,"video_count":5,"sentence_id":"354357","drift_info":null,"sentence_tag":2004,"word_cover":{"uri":"tos-cn-p-0015/e01944a0e1f94e75932a5686ce689f96_1626508345","url_list":["https://p29.douyinpic.com/img/tos-cn-p-0015/e01944a0e1f94e75932a5686ce689f96_1626508345~noop.jpeg?from=3218412987","https://p26.douyinpic.com/img/tos-cn-p-0015/e01944a0e1f94e75932a5686ce689f96_1626508345~noop.jpeg?from=3218412987","https://p3.douyinpic.com/img/tos-cn-p-0015/e01944a0e1f94e75932a5686ce689f96_1626508345~noop.jpeg?from=3218412987"]},"position":11},{"hot_value":7317263,"word_cover":{"uri":"tos-cn-p-0015/a5c859a4dcba4fae8f29ec3d16eb1bb7_1626318653","url_list":["https://p3.douyinpic.com/img/tos-cn-p-0015/a5c859a4dcba4fae8f29ec3d16eb1bb7_1626318653~noop.jpeg?from=3218412987","https://p26.douyinpic.com/img/tos-cn-p-0015/a5c859a4dcba4fae8f29ec3d16eb1bb7_1626318653~noop.jpeg?from=3218412987","https://p29.douyinpic.com/img/tos-cn-p-0015/a5c859a4dcba4fae8f29ec3d16eb1bb7_1626318653~noop.jpeg?from=3218412987"]},"video_count":51,"sentence_id":"353246","related_words":null,"event_time":1626413269,"hotlist_param":"{\"version\":1}","group_id":"6984648027077498149","word_type":1,"view_count":47118655,"drift_info":null,"aweme_infos":null,"word":"随手拍封面挑战","label":5,"challenge_id":"","position":12,"sentence_tag":1003},{"word_cover":{"uri":"tos-cn-p-0015/2a2d6bb19c3545aead837c392670f015","url_list":["https://p9.douyinpic.com/img/tos-cn-p-0015/2a2d6bb19c3545aead837c392670f015~noop.jpeg?from=3218412987","https://p6.douyinpic.com/img/tos-cn-p-0015/2a2d6bb19c3545aead837c392670f015~noop.jpeg?from=3218412987","https://p3.douyinpic.com/img/tos-cn-p-0015/2a2d6bb19c3545aead837c392670f015~noop.jpeg?from=3218412987"]},"position":13,"view_count":43489864,"word":"二哥导演回应为什么选中胡先煦","hot_value":7265078,"video_count":2,"word_type":1,"related_words":null,"drift_info":null,"aweme_infos":null,"can_extend_detail":false,"event_time":1626492333,"hotlist_param":"{\"version\":1}","label":5,"challenge_id":"","group_id":"6985411703349859599","sentence_id":"353980","sentence_tag":2001},{"challenge_id":"","video_count":4,"sentence_id":"353965","view_count":42951382,"drift_info":null,"aweme_infos":null,"word":"周艺轩同王一博李汶翰杜华比耶","hot_value":7219502,"word_type":1,"event_time":1626490576,"related_words":null,"sentence_tag":2004,"label":5,"word_cover":{"uri":"tos-cn-p-0015/c93fab2fb2544ee7b6ce7c335f7f806f","url_list":["https://p29.douyinpic.com/img/tos-cn-p-0015/c93fab2fb2544ee7b6ce7c335f7f806f~noop.jpeg?from=3218412987","https://p26.douyinpic.com/img/tos-cn-p-0015/c93fab2fb2544ee7b6ce7c335f7f806f~noop.jpeg?from=3218412987","https://p3.douyinpic.com/img/tos-cn-p-0015/c93fab2fb2544ee7b6ce7c335f7f806f~noop.jpeg?from=3218412987"]},"group_id":"6985676070914577667","can_extend_detail":false,"position":14,"hotlist_param":"{\"version\":1}"},{"hot_value":7201617,"word_type":1,"related_words":null,"view_count":41912265,"hotlist_param":"{\"version\":1}","label":0,"video_count":2,"group_id":"6985676520631604491","challenge_id":"","word_cover":{"uri":"tos-cn-p-0015/8633d3be5823404b97ceb2b5158b3863_1626491461","url_list":["https://p9.douyinpic.com/img/tos-cn-p-0015/8633d3be5823404b97ceb2b5158b3863_1626491461~noop.jpeg?from=3218412987","https://p6.douyinpic.com/img/tos-cn-p-0015/8633d3be5823404b97ceb2b5158b3863_1626491461~noop.jpeg?from=3218412987","https://p29.douyinpic.com/img/tos-cn-p-0015/8633d3be5823404b97ceb2b5158b3863_1626491461~noop.jpeg?from=3218412987"]},"aweme_infos":null,"sentence_tag":2004,"word":"毛不易好守男德","sentence_id":"353992","event_time":1626493251,"drift_info":null,"position":15},{"word":"厨房历险记为颖儿定制专属冰粉","event_time":1626520276,"drift_info":null,"sentence_tag":2004,"label":5,"challenge_id":"","video_count":3,"sentence_id":"354363","hotlist_param":"{\"version\":1}","aweme_infos":null,"position":16,"hot_value":7178112,"word_cover":{"uri":"tos-cn-p-0015/06db7479fff543bda4b80cb00fd79d0b_1626516101","url_list":["https://p6.douyinpic.com/img/tos-cn-p-0015/06db7479fff543bda4b80cb00fd79d0b_1626516101~noop.jpeg?from=3218412987","https://p3.douyinpic.com/img/tos-cn-p-0015/06db7479fff543bda4b80cb00fd79d0b_1626516101~noop.jpeg?from=3218412987","https://p29.douyinpic.com/img/tos-cn-p-0015/06db7479fff543bda4b80cb00fd79d0b_1626516101~noop.jpeg?from=3218412987"]},"group_id":"6985421035601810719","word_type":1,"related_words":null,"view_count":41561459},{"word":"乐华家族演唱会红毯","hot_value":7157918,"word_cover":{"uri":"tos-cn-p-0015/9f2f8fc92f2344a7858d2cf3f367f4a2","url_list":["https://p6.douyinpic.com/img/tos-cn-p-0015/9f2f8fc92f2344a7858d2cf3f367f4a2~noop.jpeg?from=3218412987","https://p3.douyinpic.com/img/tos-cn-p-0015/9f2f8fc92f2344a7858d2cf3f367f4a2~noop.jpeg?from=3218412987","https://p26.douyinpic.com/img/tos-cn-p-0015/9f2f8fc92f2344a7858d2cf3f367f4a2~noop.jpeg?from=3218412987"]},"event_time":1626447457,"aweme_infos":null,"sentence_id":"353878","drift_info":null,"sentence_tag":2004,"challenge_id":"","position":17,"video_count":3,"can_extend_detail":false,"room_count":0,"group_id":"6985411766676608271","word_type":1,"view_count":38995515,"hotlist_param":"{\"version\":1}","label":3,"related_words":null},{"video_count":15,"drift_info":null,"hotlist_param":"{\"version\":1}","label":3,"challenge_id":"","aweme_infos":null,"can_extend_detail":false,"view_count":48447120,"sentence_tag":4003,"group_id":"6984651051236693255","related_words":null,"word_cover":{"uri":"tos-cn-p-0015/dbd6c92b875041cfac71ccdd03fb88da","url_list":["https://p3.douyinpic.com/img/tos-cn-p-0015/dbd6c92b875041cfac71ccdd03fb88da~noop.jpeg?from=3218412987","https://p26.douyinpic.com/img/tos-cn-p-0015/dbd6c92b875041cfac71ccdd03fb88da~noop.jpeg?from=3218412987","https://p29.douyinpic.com/img/tos-cn-p-0015/dbd6c92b875041cfac71ccdd03fb88da~noop.jpeg?from=3218412987"]},"position":18,"word_type":1,"room_count":0,"sentence_id":"353355","event_time":1626331759,"word":"金毛Siri主人发声","hot_value":7069991},{"sentence_id":"353649","hot_value":7058032,"challenge_id":"","position":19,"view_count":38736401,"hotlist_param":"{\"version\":1}","label":8,"word_cover":{"uri":"tos-cn-p-0015/1a9ce9f0ade546109a56cb18bd66d148","url_list":["https://p26.douyinpic.com/img/tos-cn-p-0015/1a9ce9f0ade546109a56cb18bd66d148~noop.jpeg?from=3218412987","https://p9.douyinpic.com/img/tos-cn-p-0015/1a9ce9f0ade546109a56cb18bd66d148~noop.jpeg?from=3218412987","https://p3.douyinpic.com/img/tos-cn-p-0015/1a9ce9f0ade546109a56cb18bd66d148~noop.jpeg?from=3218412987"]},"video_count":161,"group_id":"6978599735171814663","word_type":1,"related_words":null,"drift_info":null,"aweme_infos":null,"sentence_tag":1001,"word":"夺冠变装挑战","event_time":1626430815},{"word":"连平底锅都不用的无油厚蛋烧","word_cover":{"uri":"tos-cn-p-0015/f96583bce12543318ba4deec005183ef_1626411231","url_list":["https://p26.douyinpic.com/img/tos-cn-p-0015/f96583bce12543318ba4deec005183ef_1626411231~noop.jpeg?from=3218412987","https://p9.douyinpic.com/img/tos-cn-p-0015/f96583bce12543318ba4deec005183ef_1626411231~noop.jpeg?from=3218412987","https://p29.douyinpic.com/img/tos-cn-p-0015/f96583bce12543318ba4deec005183ef_1626411231~noop.jpeg?from=3218412987"]},"word_type":1,"sentence_id":"353710","hotlist_param":"{\"version\":1}","aweme_infos":null,"hot_value":7038592,"video_count":17,"group_id":"6985410275927528717","view_count":37131102,"sentence_tag":9000,"challenge_id":"","position":20,"label":3,"event_time":1626433049,"related_words":null,"drift_info":null},{"event_time":1626506012,"hotlist_param":"{\"version\":1}","sentence_tag":2004,"label":3,"hot_value":7036354,"word_type":1,"sentence_id":"354139","word":"王彦霖艾佳妮婚礼","related_words":null,"view_count":33024822,"drift_info":null,"group_id":"6963484374654768423","can_extend_detail":false,"aweme_infos":null,"challenge_id":"","word_cover":{"uri":"tos-cn-p-0015/7dcb4f4bb6534d6e81da69448f143dce","url_list":["https://p29.douyinpic.com/img/tos-cn-p-0015/7dcb4f4bb6534d6e81da69448f143dce~noop.jpeg?from=3218412987","https://p9.douyinpic.com/img/tos-cn-p-0015/7dcb4f4bb6534d6e81da69448f143dce~noop.jpeg?from=3218412987","https://p26.douyinpic.com/img/tos-cn-p-0015/7dcb4f4bb6534d6e81da69448f143dce~noop.jpeg?from=3218412987"]},"position":21,"video_count":2},{"aweme_infos":null,"word":"王一博终于长大了","hot_value":7006977,"challenge_id":"","position":22,"word_type":1,"event_time":1626485161,"drift_info":null,"label":3,"video_count":18,"sentence_id":"353946","related_words":null,"view_count":29999749,"hotlist_param":"{\"version\":1}","sentence_tag":2004,"group_id":"6855126898456925453","word_cover":{"uri":"tos-cn-p-0015/9922469fa4a34d34abf41e02a730382d_1626452424","url_list":["https://p3.douyinpic.com/img/tos-cn-p-0015/9922469fa4a34d34abf41e02a730382d_1626452424~noop.jpeg?from=3218412987","https://p29.douyinpic.com/img/tos-cn-p-0015/9922469fa4a34d34abf41e02a730382d_1626452424~noop.jpeg?from=3218412987","https://p6.douyinpic.com/img/tos-cn-p-0015/9922469fa4a34d34abf41e02a730382d_1626452424~noop.jpeg?from=3218412987"]}},{"video_count":15,"sentence_id":"354071","related_words":null,"drift_info":null,"aweme_infos":null,"label":3,"hot_value":6998251,"position":23,"word_type":1,"group_id":"6985414534115661090","hotlist_param":"{\"version\":1}","sentence_tag":2001,"view_count":30879002,"word":"詹姆斯电影评分不佳","challenge_id":"","word_cover":{"url_list":["https://p6.douyinpic.com/img/tos-cn-p-0015/56c88d22914e4d12987df70cc8efa737~noop.jpeg?from=3218412987","https://p9.douyinpic.com/img/tos-cn-p-0015/56c88d22914e4d12987df70cc8efa737~noop.jpeg?from=3218412987","https://p26.douyinpic.com/img/tos-cn-p-0015/56c88d22914e4d12987df70cc8efa737~noop.jpeg?from=3218412987"],"uri":"tos-cn-p-0015/56c88d22914e4d12987df70cc8efa737"},"event_time":1626502209},{"group_id":"6985414985230259493","event_time":1626485338,"related_words":null,"video_count":3,"view_count":29981520,"aweme_infos":null,"sentence_tag":1001,"drift_info":null,"word":"当凌云遇到唐梓","label":5,"challenge_id":"","position":24,"word_type":1,"sentence_id":"353949","hot_value":6993131,"word_cover":{"uri":"tos-cn-p-0015/640f1f83c183459c87bc898f6188233e_1626411151","url_list":["https://p6.douyinpic.com/img/tos-cn-p-0015/640f1f83c183459c87bc898f6188233e_1626411151~noop.jpeg?from=3218412987","https://p3.douyinpic.com/img/tos-cn-p-0015/640f1f83c183459c87bc898f6188233e_1626411151~noop.jpeg?from=3218412987","https://p29.douyinpic.com/img/tos-cn-p-0015/640f1f83c183459c87bc898f6188233e_1626411151~noop.jpeg?from=3218412987"]},"hotlist_param":"{\"version\":1}"},{"group_id":"6985410125787960613","sentence_id":"353602","event_time":1626429094,"position":25,"label":5,"challenge_id":"","word_cover":{"uri":"tos-cn-p-0015/a767907b241b4c5eb449321e0c2b90e2_1626419951","url_list":["https://p3.douyinpic.com/img/tos-cn-p-0015/a767907b241b4c5eb449321e0c2b90e2_1626419951~noop.jpeg?from=3218412987","https://p26.douyinpic.com/img/tos-cn-p-0015/a767907b241b4c5eb449321e0c2b90e2_1626419951~noop.jpeg?from=3218412987","https://p9.douyinpic.com/img/tos-cn-p-0015/a767907b241b4c5eb449321e0c2b90e2_1626419951~noop.jpeg?from=3218412987"]},"word_type":1,"related_words":null,"view_count":29707914,"hotlist_param":"{\"version\":1}","word":"当音乐人开始集体合唱","drift_info":null,"aweme_infos":null,"sentence_tag":1002,"hot_value":6977028,"video_count":73},{"position":26,"group_id":"6657509051569542407","sentence_id":"353773","aweme_infos":null,"label":3,"challenge_id":"","word_cover":{"uri":"tos-cn-p-0015/6549000e2646428fa8a946ae3407308b","url_list":["https://p3.douyinpic.com/img/tos-cn-p-0015/6549000e2646428fa8a946ae3407308b~noop.jpeg?from=3218412987","https://p26.douyinpic.com/img/tos-cn-p-0015/6549000e2646428fa8a946ae3407308b~noop.jpeg?from=3218412987","https://p29.douyinpic.com/img/tos-cn-p-0015/6549000e2646428fa8a946ae3407308b~noop.jpeg?from=3218412987"]},"sentence_tag":18000,"hot_value":6926975,"word_type":1,"related_words":null,"video_count":11,"event_time":1626437789,"view_count":26132316,"word":"神模仿迈克尔杰克逊","drift_info":null,"hotlist_param":"{\"version\":1}"},{"sentence_tag":5000,"sentence_id":"354283","related_words":null,"aweme_infos":null,"position":27,"drift_info":null,"group_id":"6985408951270036744","word_type":1,"label":1,"hot_value":6911762,"word_cover":{"uri":"tos-cn-p-0015/3b22473fc61a4156a3a8d1abc6cea03d_1626499553","url_list":["https://p29.douyinpic.com/img/tos-cn-p-0015/3b22473fc61a4156a3a8d1abc6cea03d_1626499553~noop.jpeg?from=3218412987","https://p26.douyinpic.com/img/tos-cn-p-0015/3b22473fc61a4156a3a8d1abc6cea03d_1626499553~noop.jpeg?from=3218412987","https://p6.douyinpic.com/img/tos-cn-p-0015/3b22473fc61a4156a3a8d1abc6cea03d_1626499553~noop.jpeg?from=3218412987"]},"event_time":1626513912,"view_count":24228326,"hotlist_param":"{\"version\":1}","word":"雄鹿太阳谁能赢下天王山之战","challenge_id":"","video_count":11},{"label":3,"word_type":1,"drift_info":null,"hot_value":6911143,"word_cover":{"uri":"tos-cn-p-0015/04d53bb121574dae8c5b511496267368","url_list":["https://p26.douyinpic.com/img/tos-cn-p-0015/04d53bb121574dae8c5b511496267368~noop.jpeg?from=3218412987","https://p29.douyinpic.com/img/tos-cn-p-0015/04d53bb121574dae8c5b511496267368~noop.jpeg?from=3218412987","https://p6.douyinpic.com/img/tos-cn-p-0015/04d53bb121574dae8c5b511496267368~noop.jpeg?from=3218412987"]},"event_time":1626438842,"aweme_infos":null,"sentence_id":"353796","view_count":23985836,"sentence_tag":2001,"word":"彭昱畅回应变瘦","challenge_id":"","position":28,"video_count":17,"group_id":"6985410145086559525","related_words":null,"hotlist_param":"{\"version\":1}"},{"label":3,"video_count":6,"event_time":1626483108,"drift_info":null,"aweme_infos":null,"word":"彭昱畅张子枫被吓成表情包","challenge_id":"","view_count":23349004,"hotlist_param":"{\"version\":1}","sentence_tag":2003,"hot_value":6866824,"position":29,"can_extend_detail":false,"sentence_id":"353936","related_words":null,"word_cover":{"uri":"tos-cn-p-0015/700cac476220493e8a9b1cdc5b2f4cc8_1626449492","url_list":["https://p26.douyinpic.com/img/tos-cn-p-0015/700cac476220493e8a9b1cdc5b2f4cc8_1626449492~noop.jpeg?from=3218412987","https://p9.douyinpic.com/img/tos-cn-p-0015/700cac476220493e8a9b1cdc5b2f4cc8_1626449492~noop.jpeg?from=3218412987","https://p29.douyinpic.com/img/tos-cn-p-0015/700cac476220493e8a9b1cdc5b2f4cc8_1626449492~noop.jpeg?from=3218412987"]},"group_id":"6985413198985090335","word_type":1},{"challenge_id":"","word_type":1,"aweme_infos":null,"position":30,"video_count":2,"group_id":"6985419653691823367","view_count":20984906,"drift_info":null,"sentence_tag":2004,"hot_value":6851717,"word_cover":{"uri":"tos-cn-p-0015/a2523d62d2234ea68f3ad515910f5f35_1626511666","url_list":["https://p9.douyinpic.com/img/tos-cn-p-0015/a2523d62d2234ea68f3ad515910f5f35_1626511666~noop.jpeg?from=3218412987","https://p29.douyinpic.com/img/tos-cn-p-0015/a2523d62d2234ea68f3ad515910f5f35_1626511666~noop.jpeg?from=3218412987","https://p3.douyinpic.com/img/tos-cn-p-0015/a2523d62d2234ea68f3ad515910f5f35_1626511666~noop.jpeg?from=3218412987"]},"event_time":1626512894,"related_words":null,"hotlist_param":"{\"version\":1}","word":"赵雅芝重回西湖唱青城山下白素贞","label":8,"sentence_id":"354262"},{"label":5,"hot_value":6838851,"related_words":null,"drift_info":null,"word_type":1,"event_time":1626409573,"sentence_tag":5000,"word_cover":{"uri":"tos-cn-p-0015/50139649e18644bc95966c9070a1e28c","url_list":["https://p26.douyinpic.com/img/tos-cn-p-0015/50139649e18644bc95966c9070a1e28c~noop.jpeg?from=3218412987","https://p9.douyinpic.com/img/tos-cn-p-0015/50139649e18644bc95966c9070a1e28c~noop.jpeg?from=3218412987","https://p6.douyinpic.com/img/tos-cn-p-0015/50139649e18644bc95966c9070a1e28c~noop.jpeg?from=3218412987"]},"position":31,"group_id":"6984665767791023397","sentence_id":"353203","view_count":19948916,"aweme_infos":null,"word":"张国伟物理班开课了","challenge_id":"","video_count":3,"can_extend_detail":false,"hotlist_param":"{\"version\":1}"},{"label":3,"hot_value":6814055,"related_words":null,"view_count":13712771,"sentence_tag":20005,"word":"如何看待金毛siri托运致死","position":32,"group_id":"6984664905501873415","room_count":0,"hotlist_param":"{\"version\":1}","challenge_id":"","word_cover":{"uri":"tos-cn-p-0015/85e428924eb743e69fe949cb3a327f33","url_list":["https://p3.douyinpic.com/img/tos-cn-p-0015/85e428924eb743e69fe949cb3a327f33~noop.jpeg?from=3218412987","https://p6.douyinpic.com/img/tos-cn-p-0015/85e428924eb743e69fe949cb3a327f33~noop.jpeg?from=3218412987","https://p9.douyinpic.com/img/tos-cn-p-0015/85e428924eb743e69fe949cb3a327f33~noop.jpeg?from=3218412987"]},"video_count":60,"can_extend_detail":false,"word_type":1,"sentence_id":"353201","event_time":1626409525,"drift_info":null,"aweme_infos":null},{"hotlist_param":"{\"version\":1}","aweme_infos":null,"hot_value":6796749,"challenge_id":"","position":33,"can_extend_detail":true,"view_count":47703427,"drift_info":null,"detail_info":{},"group_id":"6985415508103910670","word_type":1,"sentence_id":"353956","event_time":1626488690,"label":3,"video_count":2,"word":"一甜Elaine吴亦凡聊天记录","word_cover":{"uri":"tos-cn-p-0015/a3d8c1fe463a48a0b547bbb61e9e0551","url_list":["https://p3.douyinpic.com/img/tos-cn-p-0015/a3d8c1fe463a48a0b547bbb61e9e0551~noop.jpeg?from=3218412987","https://p29.douyinpic.com/img/tos-cn-p-0015/a3d8c1fe463a48a0b547bbb61e9e0551~noop.jpeg?from=3218412987","https://p9.douyinpic.com/img/tos-cn-p-0015/a3d8c1fe463a48a0b547bbb61e9e0551~noop.jpeg?from=3218412987"]},"related_words":null,"sentence_tag":2004},{"view_count":44443610,"hotlist_param":"{\"version\":1}","event_time":1626397430,"drift_info":null,"label":3,"challenge_id":"","word_cover":{"url_list":["https://p6.douyinpic.com/img/tos-cn-p-0015/519a10a6675e468bbd44b50527013fc6~noop.jpeg?from=3218412987","https://p29.douyinpic.com/img/tos-cn-p-0015/519a10a6675e468bbd44b50527013fc6~noop.jpeg?from=3218412987","https://p9.douyinpic.com/img/tos-cn-p-0015/519a10a6675e468bbd44b50527013fc6~noop.jpeg?from=3218412987"],"uri":"tos-cn-p-0015/519a10a6675e468bbd44b50527013fc6"},"video_count":119,"group_id":"6984613898407548199","hot_value":6776638,"position":34,"word_type":1,"sentence_tag":17000,"word":"尿床舞有多魔性","sentence_id":"353068","related_words":null,"aweme_infos":null},{"hot_value":6730990,"sentence_id":"353152","related_words":null,"challenge_id":"","word_cover":{"uri":"tos-cn-p-0015/14de8eadeaf0494fa63cbbd01e20ed2f_1626343287","url_list":["https://p3.douyinpic.com/img/tos-cn-p-0015/14de8eadeaf0494fa63cbbd01e20ed2f_1626343287~noop.jpeg?from=3218412987","https://p26.douyinpic.com/img/tos-cn-p-0015/14de8eadeaf0494fa63cbbd01e20ed2f_1626343287~noop.jpeg?from=3218412987","https://p29.douyinpic.com/img/tos-cn-p-0015/14de8eadeaf0494fa63cbbd01e20ed2f_1626343287~noop.jpeg?from=3218412987"]},"video_count":85,"label":3,"group_id":"6982948116119049513","aweme_infos":null,"word":"尿床歌后续","position":35,"word_type":1,"event_time":1626405782,"view_count":47114932,"drift_info":null,"hotlist_param":"{\"version\":1}","sentence_tag":20003},{"video_count":61,"sentence_id":"353690","related_words":null,"label":5,"view_count":15220484,"hotlist_param":"{\"version\":1}","sentence_tag":16000,"word":"美有姬本姬wink手势杀","word_cover":{"uri":"tos-cn-p-0015/48dbb6e8f12d4a83a0ee61aa202b8170","url_list":["https://p6.douyinpic.com/img/tos-cn-p-0015/48dbb6e8f12d4a83a0ee61aa202b8170~noop.jpeg?from=3218412987","https://p9.douyinpic.com/img/tos-cn-p-0015/48dbb6e8f12d4a83a0ee61aa202b8170~noop.jpeg?from=3218412987","https://p26.douyinpic.com/img/tos-cn-p-0015/48dbb6e8f12d4a83a0ee61aa202b8170~noop.jpeg?from=3218412987"]},"event_time":1626432353,"drift_info":null,"aweme_infos":null,"hot_value":6622752,"challenge_id":"","position":36,"group_id":"6985413251937490209","word_type":1},{"drift_info":null,"hotlist_param":"{\"version\":1}","hot_value":6620656,"group_id":"6894403180719232264","event_time":1626397900,"challenge_id":"","word_type":1,"related_words":null,"position":37,"video_count":4,"can_extend_detail":false,"sentence_id":"353072","view_count":14478801,"aweme_infos":null,"sentence_tag":20003,"word":"刘浩存情商","label":3,"word_cover":{"uri":"tos-cn-p-0015/5a9739ac545844fc932c84be5b6f7053_1626395348","url_list":["https://p9.douyinpic.com/img/tos-cn-p-0015/5a9739ac545844fc932c84be5b6f7053_1626395348~noop.jpeg?from=3218412987","https://p29.douyinpic.com/img/tos-cn-p-0015/5a9739ac545844fc932c84be5b6f7053_1626395348~noop.jpeg?from=3218412987","https://p3.douyinpic.com/img/tos-cn-p-0015/5a9739ac545844fc932c84be5b6f7053_1626395348~noop.jpeg?from=3218412987"]}},{"view_count":13544756,"can_extend_detail":false,"sentence_id":"353344","event_time":1626417480,"drift_info":null,"aweme_infos":null,"word":"和最好的朋友看燃野少年的天空","video_count":21,"group_id":"6978670838460929293","word_type":1,"hotlist_param":"{\"version\":1}","label":5,"hot_value":6561438,"word_cover":{"uri":"tos-cn-p-0015/371f192cbba04547b3639608a0d424ac_1626404410","url_list":["https://p3.douyinpic.com/img/tos-cn-p-0015/371f192cbba04547b3639608a0d424ac_1626404410~noop.jpeg?from=3218412987","https://p29.douyinpic.com/img/tos-cn-p-0015/371f192cbba04547b3639608a0d424ac_1626404410~noop.jpeg?from=3218412987","https://p9.douyinpic.com/img/tos-cn-p-0015/371f192cbba04547b3639608a0d424ac_1626404410~noop.jpeg?from=3218412987"]},"sentence_tag":2001,"challenge_id":"","position":38,"related_words":null},{"label":0,"word_cover":{"uri":"tos-cn-p-0015/236068381b79431b94f012118c273a3f","url_list":["https://p9.douyinpic.com/img/tos-cn-p-0015/236068381b79431b94f012118c273a3f~noop.jpeg?from=3218412987","https://p29.douyinpic.com/img/tos-cn-p-0015/236068381b79431b94f012118c273a3f~noop.jpeg?from=3218412987","https://p3.douyinpic.com/img/tos-cn-p-0015/236068381b79431b94f012118c273a3f~noop.jpeg?from=3218412987"]},"group_id":"6985416266769569032","can_extend_detail":false,"sentence_id":"354010","related_words":null,"aweme_infos":null,"challenge_id":"","position":39,"drift_info":null,"word":"都美竹转账记录","hot_value":6527085,"view_count":18285522,"hotlist_param":"{\"version\":1}","video_count":3,"word_type":1,"event_time":1626496433,"sentence_tag":2004},{"can_extend_detail":false,"event_time":1626504725,"drift_info":null,"aweme_infos":null,"word_cover":{"uri":"tos-cn-p-0015/c1f3c5f155ad4031bdee2faf18278789","url_list":["https://p3.douyinpic.com/img/tos-cn-p-0015/c1f3c5f155ad4031bdee2faf18278789~noop.jpeg?from=3218412987","https://p29.douyinpic.com/img/tos-cn-p-0015/c1f3c5f155ad4031bdee2faf18278789~noop.jpeg?from=3218412987","https://p26.douyinpic.com/img/tos-cn-p-0015/c1f3c5f155ad4031bdee2faf18278789~noop.jpeg?from=3218412987"]},"position":40,"video_count":3,"view_count":48022791,"hot_value":6521630,"sentence_id":"354113","related_words":null,"hotlist_param":"{\"version\":1}","word":"于晓光秋瓷炫发文回应","label":0,"challenge_id":"","group_id":"6985417595310642440","word_type":1,"sentence_tag":2004},{"view_count":46186178,"aweme_infos":null,"can_extend_detail":false,"related_words":null,"group_id":"6985411435367355686","sentence_id":"353413","position":41,"video_count":12,"sentence_tag":4003,"hot_value":6513974,"challenge_id":"","word_cover":{"uri":"tos-cn-p-0015/ad41bcef1ae14ae4bc839f67c06810ad","url_list":["https://p6.douyinpic.com/img/tos-cn-p-0015/ad41bcef1ae14ae4bc839f67c06810ad~noop.jpeg?from=3218412987","https://p3.douyinpic.com/img/tos-cn-p-0015/ad41bcef1ae14ae4bc839f67c06810ad~noop.jpeg?from=3218412987","https://p29.douyinpic.com/img/tos-cn-p-0015/ad41bcef1ae14ae4bc839f67c06810ad~noop.jpeg?from=3218412987"]},"word_type":1,"event_time":1626348636,"drift_info":null,"word":"达人用漫画为金毛Siri发声","label":0,"hotlist_param":"{\"version\":1}"},{"label":3,"video_count":3,"group_id":"6985408766067053832","sentence_id":"353488","view_count":47084772,"drift_info":null,"hotlist_param":"{\"version\":1}","aweme_infos":null,"hot_value":6493024,"challenge_id":"","word_cover":{"uri":"tos-cn-p-0015/c4c51420e83849b584bb67f7819f4f8e","url_list":["https://p3.douyinpic.com/img/tos-cn-p-0015/c4c51420e83849b584bb67f7819f4f8e~noop.jpeg?from=3218412987","https://p6.douyinpic.com/img/tos-cn-p-0015/c4c51420e83849b584bb67f7819f4f8e~noop.jpeg?from=3218412987","https://p9.douyinpic.com/img/tos-cn-p-0015/c4c51420e83849b584bb67f7819f4f8e~noop.jpeg?from=3218412987"]},"related_words":null,"sentence_tag":20002,"position":42,"event_time":1626424999,"word":"铁山靠收安妮为徒满眼温柔","word_type":1},{"related_words":null,"sentence_tag":1001,"position":43,"video_count":17,"event_time":1626438899,"view_count":10228536,"drift_info":null,"aweme_infos":null,"word":"有效美有姬","label":0,"word_cover":{"uri":"tos-cn-p-0015/f1046c57ed8e4d14959410b36cacbe5b_1626348182","url_list":["https://p9.douyinpic.com/img/tos-cn-p-0015/f1046c57ed8e4d14959410b36cacbe5b_1626348182~noop.jpeg?from=3218412987","https://p6.douyinpic.com/img/tos-cn-p-0015/f1046c57ed8e4d14959410b36cacbe5b_1626348182~noop.jpeg?from=3218412987","https://p29.douyinpic.com/img/tos-cn-p-0015/f1046c57ed8e4d14959410b36cacbe5b_1626348182~noop.jpeg?from=3218412987"]},"hotlist_param":"{\"version\":1}","hot_value":6373435,"word_type":1,"sentence_id":"353797","challenge_id":"","group_id":"6977382300675265805"},{"word_type":1,"view_count":15395089,"sentence_tag":4003,"word":"重庆两幼童坠亡生父被捕","word_cover":{"uri":"tos-cn-p-0015/5712d62c27864c47b6e32623c0edc393","url_list":["https://p9.douyinpic.com/img/tos-cn-p-0015/5712d62c27864c47b6e32623c0edc393~noop.jpeg?from=3218412987","https://p29.douyinpic.com/img/tos-cn-p-0015/5712d62c27864c47b6e32623c0edc393~noop.jpeg?from=3218412987","https://p3.douyinpic.com/img/tos-cn-p-0015/5712d62c27864c47b6e32623c0edc393~noop.jpeg?from=3218412987"]},"position":44,"sentence_id":"353343","hotlist_param":"{\"version\":1}","drift_info":null,"aweme_infos":null,"hot_value":6292055,"video_count":6,"group_id":"6983689784867738915","can_extend_detail":false,"event_time":1626417402,"related_words":null,"label":0,"challenge_id":""},{"word_type":1,"event_time":1626504411,"hotlist_param":"{\"version\":1}","label":0,"hot_value":6291375,"group_id":"6985407028843861261","position":45,"video_count":6,"sentence_id":"354107","drift_info":null,"aweme_infos":null,"word":"赵丽蓉去世21周年","challenge_id":"","word_cover":{"url_list":["https://p6.douyinpic.com/img/tos-cn-p-0015/b8ac679c0328424bb17bd8266dee6cf4~noop.jpeg?from=3218412987","https://p3.douyinpic.com/img/tos-cn-p-0015/b8ac679c0328424bb17bd8266dee6cf4~noop.jpeg?from=3218412987","https://p26.douyinpic.com/img/tos-cn-p-0015/b8ac679c0328424bb17bd8266dee6cf4~noop.jpeg?from=3218412987"],"uri":"tos-cn-p-0015/b8ac679c0328424bb17bd8266dee6cf4"},"view_count":8506443,"sentence_tag":20003,"can_extend_detail":true,"related_words":null,"detail_info":{}},{"aweme_infos":null,"sentence_tag":13000,"hot_value":6272628,"word_cover":{"uri":"tos-cn-p-0015/3f9995c1ecd4468a93c85e3f02f803d4","url_list":["https://p3.douyinpic.com/img/tos-cn-p-0015/3f9995c1ecd4468a93c85e3f02f803d4~noop.jpeg?from=3218412987","https://p26.douyinpic.com/img/tos-cn-p-0015/3f9995c1ecd4468a93c85e3f02f803d4~noop.jpeg?from=3218412987","https://p6.douyinpic.com/img/tos-cn-p-0015/3f9995c1ecd4468a93c85e3f02f803d4~noop.jpeg?from=3218412987"]},"can_extend_detail":false,"view_count":7063864,"word_type":1,"related_words":null,"hotlist_param":"{\"version\":1}","word":"柯南可能也是美有姬的学生","challenge_id":"","position":46,"group_id":"6985412109337810180","drift_info":null,"label":0,"video_count":6,"sentence_id":"353582","event_time":1626428728},{"video_count":6,"drift_info":null,"sentence_tag":1001,"aweme_infos":null,"label":5,"group_id":"6985418835097261351","word_type":1,"view_count":5182574,"word":"大魔王唐梓坐过山车表情管理","challenge_id":"","word_cover":{"uri":"tos-cn-p-0015/408eac4d19d94971a1b783dea9189df5","url_list":["https://p29.douyinpic.com/img/tos-cn-p-0015/408eac4d19d94971a1b783dea9189df5~noop.jpeg?from=3218412987","https://p9.douyinpic.com/img/tos-cn-p-0015/408eac4d19d94971a1b783dea9189df5~noop.jpeg?from=3218412987","https://p3.douyinpic.com/img/tos-cn-p-0015/408eac4d19d94971a1b783dea9189df5~noop.jpeg?from=3218412987"]},"related_words":null,"hotlist_param":"{\"version\":1}","hot_value":6244835,"position":47,"sentence_id":"353948","event_time":1626485298},{"word_type":1,"event_time":1626488710,"related_words":null,"sentence_tag":2004,"word":"蔡徐坤粉丝花墙应援","word_cover":{"uri":"tos-cn-p-0015/1d9187fd2c8f435da16ad914a900bc6c_1626490471","url_list":["https://p29.douyinpic.com/img/tos-cn-p-0015/1d9187fd2c8f435da16ad914a900bc6c_1626490471~noop.jpeg?from=3218412987","https://p26.douyinpic.com/img/tos-cn-p-0015/1d9187fd2c8f435da16ad914a900bc6c_1626490471~noop.jpeg?from=3218412987","https://p3-dy-ipv6-test.byteimg.com/img/tos-cn-p-0015/1d9187fd2c8f435da16ad914a900bc6c_1626490471~noop.jpeg?from=3218412987"]},"group_id":"6953635220513150216","sentence_id":"353958","aweme_infos":null,"hot_value":6240781,"challenge_id":"","position":48,"video_count":8,"view_count":4410159,"hotlist_param":"{\"version\":1}","label":0,"drift_info":null},{"word":"试驾员带顾客体验新车出事故","event_time":1626517396,"related_words":null,"sentence_tag":4004,"label":1,"challenge_id":"","word_cover":{"uri":"tos-cn-p-0015/8f33c66d0c6447a8883cf5a27cb353fd","url_list":["https://p26.douyinpic.com/img/tos-cn-p-0015/8f33c66d0c6447a8883cf5a27cb353fd~noop.jpeg?from=3218412987","https://p6.douyinpic.com/img/tos-cn-p-0015/8f33c66d0c6447a8883cf5a27cb353fd~noop.jpeg?from=3218412987","https://p3.douyinpic.com/img/tos-cn-p-0015/8f33c66d0c6447a8883cf5a27cb353fd~noop.jpeg?from=3218412987"]},"view_count":4039462,"drift_info":null,"hot_value":6208114,"position":49,"word_type":1,"hotlist_param":"{\"version\":1}","video_count":1,"group_id":"6985421244078445837","sentence_id":"354325","aweme_infos":null},{"video_count":3,"group_id":"6985411682995639565","word_type":1,"aweme_infos":null,"sentence_tag":20003,"hot_value":6098694,"event_time":1626432835,"word":"毛毛姐唱的放空跟别人不一样","challenge_id":"","word_cover":{"uri":"tos-cn-p-0015/6da6f75426934d1c8448e980c395637e","url_list":["https://p26.douyinpic.com/img/tos-cn-p-0015/6da6f75426934d1c8448e980c395637e~noop.jpeg?from=3218412987","https://p9.douyinpic.com/img/tos-cn-p-0015/6da6f75426934d1c8448e980c395637e~noop.jpeg?from=3218412987","https://p29.douyinpic.com/img/tos-cn-p-0015/6da6f75426934d1c8448e980c395637e~noop.jpeg?from=3218412987"]},"can_extend_detail":false,"drift_info":null,"hotlist_param":"{\"version\":1}","label":0,"position":50,"sentence_id":"353702","related_words":null,"view_count":1779395}],"active_time":"2021-07-17 21:11:23","share_info":{"share_title":"我在看抖音热榜，发现最火的内容，赶快来看！","share_link_desc":"我在看抖音热榜，发现最火的内容，赶快来看！戳这里>>","share_url":"https://www.iesdouyin.com/share/billboard/?id=0"},"trending_list":[{"aweme_infos":null,"sentence_tag":1002,"event_time":1626328950,"related_words":null,"drift_info":null,"word":"多想留在你的身边","word_type":3,"group_id":"6595538672903263491","hotlist_param":"{\"version\":1}","label":5,"hot_value":0,"video_count":222,"word_cover":{"uri":"tos-cn-p-0015/2e696029b1f84212b85bf178bbcebf12","url_list":["https://p3.douyinpic.com/img/tos-cn-p-0015/2e696029b1f84212b85bf178bbcebf12~noop.jpeg?from=3218412987","https://p26.douyinpic.com/img/tos-cn-p-0015/2e696029b1f84212b85bf178bbcebf12~noop.jpeg?from=3218412987","https://p29.douyinpic.com/img/tos-cn-p-0015/2e696029b1f84212b85bf178bbcebf12~noop.jpeg?from=3218412987"]},"sentence_id":"352524"},{"label":0,"word_type":3,"drift_info":null,"sentence_tag":20002,"hot_value":0,"word_cover":{"url_list":["https://p3.douyinpic.com/img/tos-cn-p-0015/7a9a9c862b884efcb66f466fa4774c53~noop.jpeg?from=3218412987","https://p9.douyinpic.com/img/tos-cn-p-0015/7a9a9c862b884efcb66f466fa4774c53~noop.jpeg?from=3218412987","https://p6.douyinpic.com/img/tos-cn-p-0015/7a9a9c862b884efcb66f466fa4774c53~noop.jpeg?from=3218412987"],"uri":"tos-cn-p-0015/7a9a9c862b884efcb66f466fa4774c53"},"sentence_id":"352759","aweme_infos":null,"word":"人类高质量男性","video_count":15,"group_id":"6980344759672247583","event_time":1626342940,"related_words":null,"hotlist_param":"{\"version\":1}"},{"word":"万事皆可怎么了","sentence_id":"353818","related_words":null,"hotlist_param":"{\"version\":1}","sentence_tag":1002,"word_cover":{"uri":"tos-cn-p-0015/69aac75158ee4d26b88d60bd8096d13e_1626429217","url_list":["https://p26.douyinpic.com/img/tos-cn-p-0015/69aac75158ee4d26b88d60bd8096d13e_1626429217~noop.jpeg?from=3218412987","https://p6.douyinpic.com/img/tos-cn-p-0015/69aac75158ee4d26b88d60bd8096d13e_1626429217~noop.jpeg?from=3218412987","https://p29.douyinpic.com/img/tos-cn-p-0015/69aac75158ee4d26b88d60bd8096d13e_1626429217~noop.jpeg?from=3218412987"]},"group_id":"6985410565942727949","word_type":3,"aweme_infos":null,"hot_value":0,"drift_info":null,"label":0,"video_count":155,"event_time":1626439960},{"word":"韩国女生眼中的于晓光","hot_value":0,"word_type":3,"drift_info":null,"sentence_tag":2004,"label":0,"group_id":"6862671171435894019","event_time":1626429508,"sentence_id":"353619","related_words":null,"hotlist_param":"{\"version\":1}","word_cover":{"uri":"tos-cn-p-0015/fe9da076a1064931a6582372f5cfbec8_1626428776","url_list":["https://p3.douyinpic.com/img/tos-cn-p-0015/fe9da076a1064931a6582372f5cfbec8_1626428776~noop.jpeg?from=3218412987","https://p29.douyinpic.com/img/tos-cn-p-0015/fe9da076a1064931a6582372f5cfbec8_1626428776~noop.jpeg?from=3218412987","https://p9.douyinpic.com/img/tos-cn-p-0015/fe9da076a1064931a6582372f5cfbec8_1626428776~noop.jpeg?from=3218412987"]},"video_count":3,"aweme_infos":null},{"label":0,"hot_value":0,"word_type":3,"sentence_id":"353335","drift_info":null,"word":"刘蓓小黄油官宣恋情","word_cover":{"uri":"tos-cn-p-0015/edcad4c904ba465f9119bfb23b7aa8c8_1626398619","url_list":["https://p26.douyinpic.com/img/tos-cn-p-0015/edcad4c904ba465f9119bfb23b7aa8c8_1626398619~noop.jpeg?from=3218412987","https://p29.douyinpic.com/img/tos-cn-p-0015/edcad4c904ba465f9119bfb23b7aa8c8_1626398619~noop.jpeg?from=3218412987","https://p9.douyinpic.com/img/tos-cn-p-0015/edcad4c904ba465f9119bfb23b7aa8c8_1626398619~noop.jpeg?from=3218412987"]},"group_id":"6984542933295240484","event_time":1626415457,"hotlist_param":"{\"version\":1}","video_count":1,"related_words":null,"aweme_infos":null,"sentence_tag":2004}]},"ad_search_list":null,"banner_dark":{"uri":"32e5200049fac86168117","url_list":["https://p3.douyinpic.com/obj/32e5200049fac86168117?from=65706370","https://p29.douyinpic.com/obj/32e5200049fac86168117?from=65706370","https://p9.douyinpic.com/obj/32e5200049fac86168117?from=65706370"]},"banner_light":{"uri":"321f4000f703369c24604","url_list":["https://p3.douyinpic.com/obj/321f4000f703369c24604?from=65706370","https://p6.douyinpic.com/obj/321f4000f703369c24604?from=65706370","https://p26.douyinpic.com/obj/321f4000f703369c24604?from=65706370"]},"board_tabs":null}
